colopresso/__init__.py
colopresso/_colopresso.abi3.so
colopresso/_colopresso_ext.c
colopresso/core.py
colopresso/py.typed
colopresso-12.2.0.dist-info/METADATA
colopresso-12.2.0.dist-info/WHEEL
colopresso-12.2.0.dist-info/RECORD
